ChirePyToolkit/Setting.py
ChirePyToolkit/__init__.py
ChirePyToolkit/__main__.py
ChirePyToolkit-1.0.1.dist-info/LICENSE.txt
ChirePyToolkit-1.0.1.dist-info/METADATA
ChirePyToolkit-1.0.1.dist-info/WHEEL
ChirePyToolkit-1.0.1.dist-info/top_level.txt
ChirePyToolkit-1.0.1.dist-info/RECORD
