Metadata-Version: 2.1
Name: ChirePyToolkit
Version: 1.0.1
Summary: 一个方便调用的工具库，更多方便自己用的
Home-page: https://github.com/Chi-Re
Author: 炽热S
Author-email: 3531962676@qq.com
Classifier: Programming Language :: Python :: 3
Classifier: Operating System :: OS Independent
Requires-Python: >=3.6
License-File: LICENSE.txt
Requires-Dist: requests
